blpapi/__init__.pyi
blpapi/abstractsession.pyi
blpapi/auth.pyi
blpapi/chandle.pyi
blpapi/compat.pyi
blpapi/constant.pyi
blpapi/datatype.pyi
blpapi/datetime.pyi
blpapi/debug.pyi
blpapi/debug_environment.pyi
blpapi/diagnosticsutil.pyi
blpapi/element.pyi
blpapi/event.pyi
blpapi/eventdispatcher.pyi
blpapi/eventformatter.pyi
blpapi/exception.pyi
blpapi/highresclock.pyi
blpapi/identity.pyi
blpapi/internals.pyi
blpapi/logging.pyi
blpapi/message.pyi
blpapi/name.pyi
blpapi/names.pyi
blpapi/providersession.pyi
blpapi/py.typed
blpapi/request.pyi
blpapi/requesttemplate.pyi
blpapi/resolutionlist.pyi
blpapi/schema.pyi
blpapi/service.pyi
blpapi/session.pyi
blpapi/sessionoptions.pyi
blpapi/subscriptionlist.pyi
blpapi/topic.pyi
blpapi/topiclist.pyi
blpapi/utils.pyi
blpapi/version.pyi
blpapi/versionhelper.pyi
blpapi/zfputil.pyi
blpapi_stubs-0.0.2.dist-info/LICENSE
blpapi_stubs-0.0.2.dist-info/METADATA
blpapi_stubs-0.0.2.dist-info/WHEEL
blpapi_stubs-0.0.2.dist-info/top_level.txt
blpapi_stubs-0.0.2.dist-info/RECORD
