Metadata-Version: 2.1
Name: blpapi-stubs
Version: 0.0.2
Summary: Mypy stubs for blpapi
Home-page: https://github.com/sdfordham/blpapi-stubs
Author: Stiofán Fordham
Author-email: stiofan.fordham@gmail.com
License: UNKNOWN
Project-URL: Bug Tracker, https://github.com/sdfordham/blpapi-stubs/issues
Platform: UNKNOWN
Classifier: Programming Language :: Python :: 3
Classifier: License :: OSI Approved :: MIT License
Classifier: Operating System :: OS Independent
License-File: LICENSE
Requires-Dist: mypy (>=0.790)
Requires-Dist: typing-extensions (>=3.7.4)
